virheat/__init__.py
virheat/__main__.py
virheat/command.py
virheat/scripts/__init__.py
virheat/scripts/data_prep.py
virheat/scripts/plotting.py
virheat-0.7.6.dist-info/licenses/LICENSE
virheat-0.7.6.dist-info/METADATA
virheat-0.7.6.dist-info/WHEEL
virheat-0.7.6.dist-info/entry_points.txt
virheat-0.7.6.dist-info/top_level.txt
virheat-0.7.6.dist-info/RECORD
