Metadata-Version: 2.4
Name: virheat
Version: 0.7.6
Summary: virHEAT creates a heatmap from vcf files and maps positions on to a reference genome.
Author-email: Jonas Fuchs <jonas.fuchs@uniklinik-freiburg.de>
Maintainer-email: Jonas Fuchs <jonas.fuchs@uniklinik-freiburg.de>
License:                     GNU GENERAL PUBLIC LICENSE
Keywords: vcf, snp, evolution
Classifier: Programming Language :: Python :: 3.9
Classifier: Operating System :: OS Independent
Requires-Python: >=3.9
License-File: LICENSE
Requires-Dist: matplotlib>=3.5.1
Requires-Dist: numpy>=1.23.3
Requires-Dist: pandas>=1.4.4
Dynamic: license-file
